iolanta_jinja2/__init__.py
iolanta_jinja2/cli.py
iolanta_jinja2/macros.py
iolanta_jinja2/plugin.py
iolanta_jinja2/process_template.py
iolanta_jinja2-0.1.4.dist-info/METADATA
iolanta_jinja2-0.1.4.dist-info/entry_points.txt
iolanta_jinja2-0.1.4.dist-info/WHEEL
iolanta_jinja2-0.1.4.dist-info/RECORD
