Metadata-Version: 2.1
Name: iolanta-jinja2
Version: 0.1.4
Summary: Render Jinja2 templates from Iolanta graph
License: MIT
Author: Anatoly Scherbakov
Author-email: altaisoft@gmail.com
Requires-Python: >=3.10,<4.0
Classifier: License :: OSI Approved :: MIT License
Classifier: Programming Language :: Python :: 3
Classifier: Programming Language :: Python :: 3.10
Classifier: Programming Language :: Python :: 3.11
Requires-Dist: Jinja2 (>=3.1.2,<4.0.0)
Requires-Dist: iolanta (>=1.0.12,<2.0.0)
